py_configurator_logger/__init__.py
py_configurator_logger/custom_logger.py
py_configurator_logger/logger_helper.py
py_configurator_logger-1.1.dist-info/LICENSE
py_configurator_logger-1.1.dist-info/METADATA
py_configurator_logger-1.1.dist-info/WHEEL
py_configurator_logger-1.1.dist-info/top_level.txt
py_configurator_logger-1.1.dist-info/RECORD
