Metadata-Version: 2.1
Name: py_configurator_logger
Version: 1.1
Summary: A custom logger which includes json log format and plain text log format
Author: Abbas Shaikh
Author-email: abbasshxikh77@gmail.com
License: MIT
License-File: LICENSE
